jupyterlab_theme_toggler/__init__.py
jupyterlab_theme_toggler/_version.py
jupyterlab_theme_toggler-1.1.0.data/data/share/jupyter/labextensions/jupyterlab-theme-toggler/package.json
jupyterlab_theme_toggler-1.1.0.data/data/share/jupyter/labextensions/jupyterlab-theme-toggler/schemas/jupyterlab-theme-toggler/package.json.orig
jupyterlab_theme_toggler-1.1.0.data/data/share/jupyter/labextensions/jupyterlab-theme-toggler/schemas/jupyterlab-theme-toggler/plugin.json
jupyterlab_theme_toggler-1.1.0.data/data/share/jupyter/labextensions/jupyterlab-theme-toggler/static/218.19afdf46f3c2dd08cdd5.js
jupyterlab_theme_toggler-1.1.0.data/data/share/jupyter/labextensions/jupyterlab-theme-toggler/static/remoteEntry.1d63eaf454a7d5779aa0.js
jupyterlab_theme_toggler-1.1.0.data/data/share/jupyter/labextensions/jupyterlab-theme-toggler/static/style.js
jupyterlab_theme_toggler-1.1.0.data/data/share/jupyter/labextensions/jupyterlab-theme-toggler/static/third-party-licenses.json
jupyterlab_theme_toggler-1.1.0.data/data/share/jupyter/labextensions/jupyterlab-theme-toggler/install.json
jupyterlab_theme_toggler-1.1.0.dist-info/METADATA
jupyterlab_theme_toggler-1.1.0.dist-info/WHEEL
jupyterlab_theme_toggler-1.1.0.dist-info/licenses/LICENSE
jupyterlab_theme_toggler-1.1.0.dist-info/RECORD
