Metadata-Version: 2.4
Name: jupyterlab_theme_toggler
Version: 1.1.0
Dynamic: Keywords
Summary: JupyterLab Toolbar Theme Toggler
Project-URL: Homepage, https://github.com/jupyterlab-contrib/jupyterlab-topbar
Project-URL: Bug Tracker, https://github.com/jupyterlab-contrib/jupyterlab-topbar/issues
Project-URL: Repository, https://github.com/jupyterlab-contrib/jupyterlab-topbar.git
Author: jupyterlab-topbar contributors
License: BSD 3-Clause License
License-File: LICENSE
Classifier: Framework :: Jupyter
Classifier: Framework :: Jupyter :: JupyterLab
Classifier: Framework :: Jupyter :: JupyterLab :: 4
Classifier: Framework :: Jupyter :: JupyterLab :: Extensions
Classifier: Framework :: Jupyter :: JupyterLab :: Extensions :: Prebuilt
Classifier: License :: OSI Approved :: BSD License
Classifier: Programming Language :: Python
Classifier: Programming Language :: Python :: 3
Classifier: Programming Language :: Python :: 3.9
Classifier: Programming Language :: Python :: 3.10
Classifier: Programming Language :: Python :: 3.11
Classifier: Programming Language :: Python :: 3.12
Classifier: Programming Language :: Python :: 3.13
Requires-Python: >=3.9
Requires-Dist: jupyterlab<5,>=4.0.0
